gadgetron/__init__.py
gadgetron/__main__.py
gadgetron/version.py
gadgetron/examples/__init__.py
gadgetron/examples/pass_through.py
gadgetron/examples/recon_acquisitions.py
gadgetron/examples/recon_buffers.py
gadgetron/external/__init__.py
gadgetron/external/connection.py
gadgetron/external/constants.py
gadgetron/external/handlers.py
gadgetron/external/listen.py
gadgetron/external/readers.py
gadgetron/external/writers.py
gadgetron/legacy/__init__.py
gadgetron/legacy/gadget.py
gadgetron/types/__init__.py
gadgetron/types/acquisition_bucket.py
gadgetron/types/image_array.py
gadgetron/types/recon_data.py
gadgetron/util/__init__.py
gadgetron/util/cfft.py
gadgetron-1.4.1.dist-info/LICENSE
gadgetron-1.4.1.dist-info/METADATA
gadgetron-1.4.1.dist-info/WHEEL
gadgetron-1.4.1.dist-info/top_level.txt
gadgetron-1.4.1.dist-info/RECORD
