Metadata-Version: 2.1
Name: gadgetron
Version: 1.4.1
Summary: Python interface for Gadgetron
Home-page: 
Author: Kristoffer Langeland Knudsen
Author-email: kristofferlknudsen@gradientsoftware.net
License: MIT
License-File: LICENSE
Requires-Dist: numpy (>=1.22)
Requires-Dist: ismrmrd (>=1.12.5)
Requires-Dist: pyFFTW (>=0.11)
Requires-Dist: multimethod (>=1.0)
